kevins_torch/__init__.py
kevins_torch/loss_functions/__init__.py
kevins_torch/loss_functions/focal_loss.py
kevins_torch/models/__init__.py
kevins_torch/models/base.py
kevins_torch/models/cnn.py
kevins_torch/models/lenet.py
kevins_torch/models/pretrained.py
kevins_torch/models/utils/__init__.py
kevins_torch/models/utils/activation_function_parser.py
kevins_torch/utils/__init__.py
kevins_torch/utils/lightning_models.py
kevins_torch/utils/load_parameters.py
kevins_torch/utils/logger_config.py
kevins_torch/utils/repeat_channels.py
kevins_torch/utils/dataset/__init__.py
kevins_torch/utils/dataset/coffee_bean_dataset.py
tests/__init__.py
tests/test_lightning_models.py
tests/test_load_parameters.py
tests/test_models.py
tests/test_pretrained.py
kevins_torch-0.2.2.dist-info/METADATA
kevins_torch-0.2.2.dist-info/WHEEL
kevins_torch-0.2.2.dist-info/top_level.txt
kevins_torch-0.2.2.dist-info/RECORD
