Metadata-Version: 2.1
Name: kevins_torch
Version: 0.2.2
Summary: A collection of PyTorch utilities for image AI training
Home-page: https://github.com/qazsskevin/kevins_torch
Author: Kevin
Author-email: qazsskevin@gmail.com
Classifier: Programming Language :: Python :: 3
Classifier: License :: OSI Approved :: MIT License
Classifier: Operating System :: OS Independent
Requires-Python: >=3.8
Requires-Dist: torch>=2.0.0
Requires-Dist: torchvision>=0.15.0
Requires-Dist: numpy>=1.21.0
Requires-Dist: Pillow>=8.0.0
